odoo9_addon_base_manifest_extension-9.0.1.0.0.99.dev3-py2.7-nspkg.pth
odoo9_addon_base_manifest_extension-9.0.1.0.0.99.dev3.dist-info/DESCRIPTION.rst
odoo9_addon_base_manifest_extension-9.0.1.0.0.99.dev3.dist-info/METADATA
odoo9_addon_base_manifest_extension-9.0.1.0.0.99.dev3.dist-info/RECORD
odoo9_addon_base_manifest_extension-9.0.1.0.0.99.dev3.dist-info/WHEEL
odoo9_addon_base_manifest_extension-9.0.1.0.0.99.dev3.dist-info/metadata.json
odoo9_addon_base_manifest_extension-9.0.1.0.0.99.dev3.dist-info/namespace_packages.txt
odoo9_addon_base_manifest_extension-9.0.1.0.0.99.dev3.dist-info/top_level.txt
odoo_addons/base_manifest_extension/README.rst
odoo_addons/base_manifest_extension/__init__.py
odoo_addons/base_manifest_extension/__openerp__.py
odoo_addons/base_manifest_extension/hooks.py
odoo_addons/base_manifest_extension/i18n/base_manifest_extension.pot
odoo_addons/base_manifest_extension/static/description/icon.png
odoo_addons/base_manifest_extension/tests/__init__.py
odoo_addons/base_manifest_extension/tests/test_hooks.py
